[
  {
    "name": "Total number of airports",
    "title": "Total number of airports",
    "description": "Total number of airports in country",
    "type": "key figure",
    "ingredients": {
      "aggregateFunctions": [
        "count"
      ],
      "valueColumns": [
        "#meta+code"
      ]
    }
  },
  {
    "name": "Number of airports by adm1 (count)",
    "title": "Number of airports by adm1 (count)",
    "description": "Number of airports by adm1 (count)",
    "type": "chart",
    "ingredients": {
      "aggregateFunctions": [
        "count"
      ],
      "aggregateColumns": [
        "#adm1+code+iso"
      ],
      "valueColumns": [
        "#meta+code"
      ]
    }
  },
  {
    "name": "Number of airports by adm1 (sum)",
    "title": "Number of airports by adm1 (sum)",
    "description": "Number of airports by adm1 (sum)",
    "type": "chart",
    "ingredients": {
      "aggregateFunctions": [
        "distinct-count"
      ],
      "aggregateColumns": [
        "#adm1+code+iso"
      ],
      "valueColumns": [
        "#meta+code"
      ]
    }
  },
  {
    "name": "Number of airports by adm1 and loc-code (count)",
    "title": "Number of airports by adm1 and loc-code(count)",
    "description": "Number of airports by adm1 and loc-code (count)",
    "type": "chart",
    "ingredients": {
      "aggregateFunctions": [
        "count"
      ],
      "aggregateColumns": [
        "#adm1+code+iso"
      ],
      "valueColumns": [
        "#loc+airport+code"
      ]
    }
  }
]
